mattflow/__init__.py
mattflow/__main__.py
mattflow/bcmanager.py
mattflow/config.py
mattflow/dat_writer.py
mattflow/flux.py
mattflow/initializer.py
mattflow/logger.py
mattflow/mattflow_cmaps.py
mattflow/mattflow_post.py
mattflow/mattflow_solver.py
mattflow/mattflow_test.py
mattflow/utils.py
mattflow-1.4.3.dist-info/COPYING
mattflow-1.4.3.dist-info/METADATA
mattflow-1.4.3.dist-info/WHEEL
mattflow-1.4.3.dist-info/entry_points.txt
mattflow-1.4.3.dist-info/top_level.txt
mattflow-1.4.3.dist-info/RECORD
