Metadata-Version: 2.1
Name: mattflow
Version: 1.4.3
Summary: A CFD python package for the Shallow Water Equations
Home-page: https://github.com/ThanasisMattas/mattflow.git
Author: Athanasios Mattas
Author-email: thanasismatt@gmail.com
License: GNU GPL3
Platform: UNKNOWN
Classifier: Programming Language :: Python :: 3
Classifier: Natural Language :: English
Classifier: License :: OSI Approved :: GNU Lesser General Public License v3 or later (LGPLv3+)
Classifier: Operating System :: OS Independent
Requires-Dist: click (>=7.0)
Requires-Dist: numba (>=0.51.2)
Requires-Dist: numpy (>=1.18.5)
Requires-Dist: matplotlib (>=3.3.1)
Requires-Dist: joblib (>=0.13.2)
Provides-Extra: write_video
Requires-Dist: ffmpeg ; extra == 'write_video'
